texfont/__init__.py
texfont/cli.py
texfont/font/__init__.py
texfont/font/install.py
texfont/font/list.py
texfont/font_list.json
texfont/texfont.py
texfont/utils/__init__.py
texfont/utils/font_data.py
texfont/utils/test.json
texfont-0.1.10.dist-info/METADATA
texfont-0.1.10.dist-info/WHEEL
texfont-0.1.10.dist-info/entry_points.txt
texfont-0.1.10.dist-info/RECORD
